DevConsole/Console.py
DevConsole/__init__.py
DevConsole-0.2.3.dist-info/LICENSE
DevConsole-0.2.3.dist-info/METADATA
DevConsole-0.2.3.dist-info/WHEEL
DevConsole-0.2.3.dist-info/top_level.txt
DevConsole-0.2.3.dist-info/RECORD
