Metadata-Version: 2.1
Name: DevConsole
Version: 0.2.3
Summary: A Tkinter GUI Console For Executing Commands.
Home-page: https://github.com/RandomLolKid/PyConsole
Author: JasonTheDev
Author-email: examqiename@gmail.com
Classifier: Programming Language :: Python :: 3
Classifier: Operating System :: OS Independent
Requires-Python: >=3.6
License-File: LICENSE
